{
  "categories": [
    {
      "title": "Личные вещи",
      "href": "/",
      "items": [
        {
          "title": "Женские вещи",
          "href": "/"
        },
        {
          "title": "Мужские вещи",
          "href": "/"
        }
      ]
    },
    {
      "title": "Телефоны и аксессуары",
      "href": "/",
      "items": [
        {
          "title": "Мобильные телефоны",
          "href": "/",
          "links": [
            {
              "title": "Смартфоны",
              "href": "/"
            },
            {
              "title": "Xiaomi",
              "href": "/"
            },
            {
              "title": "Samsung",
              "href": "/"
            },
            {
              "title": "Honor",
              "href": "/"
            },
            {
              "title": "Huawei",
              "href": "/"
            },
            {
              "title": "Menzu",
              "href": "/"
            },
            {
              "title": "Nokia",
              "href": "/"
            },
            {
              "title": "Кнопочные телефоны",
              "href": "/"
            },
            {
              "title": "Стилусы",
              "href": "/"
            }
          ]
        },
        {
          "title": "Гаджеты",
          "href": "/",
          "links": [
            {
              "title": "Смарт-часы и браслеты",
              "href": "/"
            }
          ]
        },
        {
          "title": "Наушники и гарнитуры",
          "href": "/",
          "links": [
            {
              "title": "Проводные",
              "href": "/"
            },
            {
              "title": "Беспроводные",
              "href": "/"
            }
          ]
        },
        {
          "title": "Запчасти",
          "href": "/",
          "links": [
            {
              "title": "Дисплеи",
              "href": "/"
            },
            {
              "title": "Аккумуляторы",
              "href": "/"
            }
          ]
        },
        { "title": "Чехлы для смартфонов", "href": "/" },
        {
          "title": "Аксессуары для телефонов",
          "href": "/",
          "links": [
            {
              "title": "Зарядные устройста",
              "href": "/"
            },
            {
              "title": "Кабели и адаптеры",
              "href": "/"
            },
            {
              "title": "Внешние аккумуляторы",
              "href": "/"
            },
            {
              "title": "Чехлы",
              "href": "/"
            },
            {
              "title": "Держатели",
              "href": "/"
            },
            {
              "title": "Стилусы",
              "href": "/"
            },
            {
              "title": "Защитные стекла и пленки",
              "href": "/"
            },
            {
              "title": "Карты памяти",
              "href": "/"
            }
          ]
        }
      ]
    },
    {
      "title": "Электроника",
      "href": "/"
    },
    {
      "title": "Бытовая техника",
      "href": "/"
    },
    {
      "title": "Дом и сад",
      "href": "/"
    },
    {
      "title": "Товары для детей",
      "href": "/"
    },
    {
      "title": "Животные",
      "href": "/"
    },
    {
      "title": "Хобби и отдых",
      "href": "/"
    },
    {
      "title": "Транспорт",
      "href": "/"
    },
    {
      "title": "Автотовары",
      "href": "/"
    },
    {
      "title": "Недвижимость",
      "href": "/"
    },
    {
      "title": "Работа",
      "href": "/"
    },
    {
      "title": "Услуги",
      "href": "/"
    },
    {
      "title": "Для бизнеса",
      "href": "/"
    },
    {
      "title": "Отдам даром",
      "href": "/"
    }
  ],
  "announcement": {
    "title": "Объявления",
    "href": "/"
  },
  "stores": {
    "title": "Магазины",
    "href": "/"
  },
  "charity": {
    "title": "Благотворительность",
    "href": "/"
  },
  "btn_new_announcement": {
    "title": "Подать объявление",
    "href": "/"
  }
}
